penguin_libraries/EasyML/__init__.py
penguin_libraries/EasyML/main.py
penguin_libraries/EasyML/params.py
penguin_libraries/EasyML/utils.py
penguin_libraries/EfficientGAN/__init__.py
penguin_libraries/EfficientGAN/dataset.py
penguin_libraries/EfficientGAN/evaluate.py
penguin_libraries/EfficientGAN/main.py
penguin_libraries/EfficientGAN/models/__init__.py
penguin_libraries/EfficientGAN/models/discriminator.py
penguin_libraries/EfficientGAN/models/encoder.py
penguin_libraries/EfficientGAN/models/generator.py
penguin_libraries/EfficientGAN/models/model.py
penguin_libraries/__init__.py
penguin_libraries/templates/__init__.py
penguin_libraries/templates/dataset.py
penguin_libraries/templates/evaluate.py
penguin_libraries/templates/main.py
penguin_libraries/templates/model.py
penguin_libraries/templates/train.py
penguin_libraries-0.1.6.dist-info/WHEEL
penguin_libraries-0.1.6.dist-info/METADATA
penguin_libraries-0.1.6.dist-info/RECORD
